inline_snapshot_django/__init__.py
inline_snapshot_django/py.typed
inline_snapshot_django-1.3.0.dist-info/licenses/LICENSE
inline_snapshot_django-1.3.0.dist-info/METADATA
inline_snapshot_django-1.3.0.dist-info/WHEEL
inline_snapshot_django-1.3.0.dist-info/top_level.txt
inline_snapshot_django-1.3.0.dist-info/RECORD
