Metadata-Version: 2.4
Name: inline-snapshot-django
Version: 1.3.0
Summary: Extensions for using inline-snapshot to test Django projects.
Author-email: Adam Johnson <me@adamj.eu>
License-Expression: MIT
Project-URL: Changelog, https://inline-snapshot-django.readthedocs.io/en/latest/changelog.html
Project-URL: Documentation, https://inline-snapshot-django.readthedocs.io/
Project-URL: Funding, https://adamj.eu/books/
Project-URL: Repository, https://github.com/adamchainz/inline-snapshot-django
Keywords: Django
Classifier: Development Status :: 5 - Production/Stable
Classifier: Framework :: Django :: 4.2
Classifier: Framework :: Django :: 5.0
Classifier: Framework :: Django :: 5.1
Classifier: Framework :: Django :: 5.2
Classifier: Framework :: Django :: 6.0
Classifier: Framework :: Pytest
Classifier: Intended Audience :: Developers
Classifier: Natural Language :: English
Classifier: Operating System :: OS Independent
Classifier: Programming Language :: Python :: 3 :: Only
Classifier: Programming Language :: Python :: 3.9
Classifier: Programming Language :: Python :: 3.10
Classifier: Programming Language :: Python :: 3.11
Classifier: Programming Language :: Python :: 3.12
Classifier: Programming Language :: Python :: 3.13
Classifier: Programming Language :: Python :: 3.14
Classifier: Programming Language :: Python :: Implementation :: CPython
Classifier: Typing :: Typed
Requires-Python: >=3.9
License-File: LICENSE
Requires-Dist: django>=4.2
Requires-Dist: inline-snapshot>=0.23
Requires-Dist: sql-impressao>=1.4
Dynamic: license-file
